u_d_adj_ret/__init__.py
u_d_adj_ret/a_compute_adj_rets.py
u_d_adj_ret/b_upload_2_GitHub.py
u_d_adj_ret/main.py
u_d_adj_ret-2.0.1.dist-info/METADATA
u_d_adj_ret-2.0.1.dist-info/WHEEL
u_d_adj_ret-2.0.1.dist-info/RECORD
